odoo/addons/ssi_elearning/README.rst
odoo/addons/ssi_elearning/__init__.py
odoo/addons/ssi_elearning/__manifest__.py
odoo/addons/ssi_elearning/controllers/__init__.py
odoo/addons/ssi_elearning/controllers/main.py
odoo/addons/ssi_elearning/i18n/ssi_elearning.pot
odoo/addons/ssi_elearning/models/__init__.py
odoo/addons/ssi_elearning/models/slide_channel.py
odoo/addons/ssi_elearning/static/description/icon.png
odoo/addons/ssi_elearning/views/slide_channel_views.xml
odoo/addons/ssi_elearning/views/website_slides_templates_course.xml
odoo14_addon_ssi_elearning-14.0.1.2.0.dist-info/METADATA
odoo14_addon_ssi_elearning-14.0.1.2.0.dist-info/WHEEL
odoo14_addon_ssi_elearning-14.0.1.2.0.dist-info/top_level.txt
odoo14_addon_ssi_elearning-14.0.1.2.0.dist-info/RECORD
